logicqubit/__init__.py
logicqubit/__main__.py
logicqubit/circuit.py
logicqubit/exceptions.py
logicqubit/gates.py
logicqubit/hilbert.py
logicqubit/logic.py
logicqubit/oracle.py
logicqubit/qubits.py
logicqubit/synthesis.py
logicqubit/utils.py
logicqubit/zhegalkin.py
logicqubit_gpu-1.6.4.dist-info/LICENSE
logicqubit_gpu-1.6.4.dist-info/METADATA
logicqubit_gpu-1.6.4.dist-info/WHEEL
logicqubit_gpu-1.6.4.dist-info/top_level.txt
logicqubit_gpu-1.6.4.dist-info/RECORD
