Metadata-Version: 2.1
Name: logicqubit-gpu
Version: 1.6.4
Summary: logicqubit-gpu is a simple library for quantum computing simulation with gpu acceleration.
Home-page: https://github.com/clnrp/logicqubit-gpu
Author: Cleoner Pietralonga
Author-email: cleonerp@gmail.com
Classifier: Development Status :: 4 - Beta
Classifier: Intended Audience :: Developers
Classifier: Topic :: Scientific/Engineering :: Physics
Classifier: License :: OSI Approved :: Apache Software License
Classifier: Programming Language :: Python :: 2.7
Classifier: Programming Language :: Python :: 3
Classifier: Programming Language :: Python :: 3.4
Classifier: Programming Language :: Python :: 3.5
Classifier: Programming Language :: Python :: 3.6
Classifier: Programming Language :: Python :: 3.7
Classifier: Programming Language :: Python :: 3.8
Classifier: Programming Language :: Python :: 3.9
Classifier: Programming Language :: Python :: 3.10
Classifier: Programming Language :: Python :: 3.11
License-File: LICENSE
Requires-Dist: sympy
Requires-Dist: numpy
Requires-Dist: matplotlib
Requires-Dist: cupy-cuda12x
